{
  "bannerList": [
    {
      "hashtag": "#인도 #라다크 #히말라야",
      "title": "트래킹 없는 히말라야\n라다크 지프투어 12일",
      "img": "https://drive.google.com/file/d/1geiI5tzBIQ3X9f1AwEGhqYrJI9hFpe19/view?usp=sharing"
    },
    {
      "hashtag": "#모로코 #튀니지 #지중해 #북아프리카",
      "title": "쇼핑 없는 이탈리아\n모로코 자동차 12일",
      "img": "https://drive.google.com/file/d/1UNQDn_RAEVoGHrduRGJe65pONnaMkjLe/view?usp=sharing"
    },
    {
      "hashtag": "#영국 #라다크 #히말라야",
      "title": "6070의 버킷리스트\n중남비 9개국 31일",
      "img": "https://drive.google.com/file/d/1SPFt10HYHRmdP4Rdu7nKmNNQ66ToyoP9/view?usp=sharing"
    }
  ]
}
